metigan/__init__.py
metigan/client.py
metigan/errors.py
metigan/http_client.py
metigan/services/__init__.py
metigan/services/audiences_service.py
metigan/services/contacts_service.py
metigan/services/email_service.py
metigan/services/forms_service.py
metigan/services/templates_service.py
metigan-1.0.5.dist-info/licenses/LICENSE
metigan-1.0.5.dist-info/METADATA
metigan-1.0.5.dist-info/WHEEL
metigan-1.0.5.dist-info/top_level.txt
metigan-1.0.5.dist-info/RECORD
