Metadata-Version: 2.4
Name: metigan
Version: 1.0.5
Summary: Official Metigan SDK for Python - Email, Forms, Contacts, and Audiences management
Home-page: https://github.com/metigan/python
Author: Metigan
Author-email: Metigan <support@metigan.com>
License-Expression: MIT
Project-URL: Homepage, https://metigan.com
Project-URL: Documentation, https://docs.metigan.com
Project-URL: Repository, https://github.com/metigan/python
Project-URL: Issues, https://github.com/metigan/python/issues
Keywords: metigan,email,email-api,forms,contacts,audiences,sdk
Classifier: Development Status :: 4 - Beta
Classifier: Intended Audience :: Developers
Classifier: Programming Language :: Python :: 3
Classifier: Programming Language :: Python :: 3.8
Classifier: Programming Language :: Python :: 3.9
Classifier: Programming Language :: Python :: 3.10
Classifier: Programming Language :: Python :: 3.11
Classifier: Programming Language :: Python :: 3.12
Requires-Python: >=3.8
License-File: LICENSE
Requires-Dist: requests>=2.31.0
Dynamic: author
Dynamic: home-page
Dynamic: license-file
Dynamic: requires-python
